valutes_protobuf/__init__.py
valutes_protobuf/get_dollar_rate_pb2.py
valutes_protobuf/get_dollar_rate_twirp.py
valutes_protobuf-0.0.1.dist-info/DESCRIPTION.rst
valutes_protobuf-0.0.1.dist-info/METADATA
valutes_protobuf-0.0.1.dist-info/RECORD
valutes_protobuf-0.0.1.dist-info/WHEEL
valutes_protobuf-0.0.1.dist-info/entry_points.txt
valutes_protobuf-0.0.1.dist-info/metadata.json
valutes_protobuf-0.0.1.dist-info/top_level.txt
